pyarcknot/__init__.py
pyarcknot/knot_calculate.py
pyarcknot/knot_diagram.py
pyarcknot/knot_matrix.py
pyarcknot/turaev_surface.py
pyarcknot-0.0.2.dist-info/LICENSE.txt
pyarcknot-0.0.2.dist-info/METADATA
pyarcknot-0.0.2.dist-info/WHEEL
pyarcknot-0.0.2.dist-info/top_level.txt
pyarcknot-0.0.2.dist-info/RECORD
