Metadata-Version: 2.1
Name: pyarcknot
Version: 0.0.2
Summary: A package for studying the arc diagrams of mathematical knots
Home-page: https://github.com/inigorrix/pyarcknot
Author: inigorrix
Author-email: inigorrix@gmail.com
License: MIT
Keywords: knot,knot diagram,arc diagram,jones polynomial,turaev surface
Classifier: License :: OSI Approved :: MIT License
Classifier: Operating System :: OS Independent
Classifier: Programming Language :: Python :: 3
License-File: LICENSE.txt
Requires-Dist: matplotlib
Requires-Dist: numba
Requires-Dist: numpy
Requires-Dist: sympy
